README.md
RyGames-0.1a13.dist-info/DESCRIPTION.rst
RyGames-0.1a13.dist-info/METADATA
RyGames-0.1a13.dist-info/RECORD
RyGames-0.1a13.dist-info/WHEEL
RyGames-0.1a13.dist-info/metadata.json
RyGames-0.1a13.dist-info/top_level.txt
rygames/CoinGame.py
rygames/CountryGuessingGame.py
rygames/Hangman.py
rygames/TicTacToe1Player.py
rygames/TicTacToe2Player.py
rygames/TwentyFortyEight.py
rygames/Warships.py
rygames/__AIFleets__.py
rygames/__AIShots__.py
rygames/__init__.py
