Metadata-Version: 2.0
Name: RyGames
Version: 0.1a13
Summary: Python games by Ryan J. Slater
Home-page: https://github.com/rjslater2000/RyGames
Author: Ryan J. Slater
Author-email: ryan.j.slater.2@gmail.com
License: UNKNOWN
Keywords: games,battleship,python
Platform: UNKNOWN
Requires-Dist: PyDictionary
Requires-Dist: matplotlib
Requires-Dist: names
Requires-Dist: nltk
Requires-Dist: numpy
Requires-Dist: pygame
